docassemble/__init__.py
docassemble/ALToolbox/Addup.py
docassemble/ALToolbox/PhoneNumberDataType.py
docassemble/ALToolbox/ThreePartsDate.py
docassemble/ALToolbox/__init__.py
docassemble/ALToolbox/addenda.py
docassemble/ALToolbox/al_income.py
docassemble/ALToolbox/business_days.py
docassemble/ALToolbox/copy_button.py
docassemble/ALToolbox/display_template.py
docassemble/ALToolbox/llms.py
docassemble/ALToolbox/misc.py
docassemble/ALToolbox/py.typed
docassemble/ALToolbox/requirements.txt
docassemble/ALToolbox/save_input_data.py
docassemble/ALToolbox/test_al_income.py
docassemble/ALToolbox/test_altoolbox.py
docassemble/ALToolbox/test_misc.py
docassemble/ALToolbox/data/questions/Addup.yml
docassemble/ALToolbox/data/questions/Bells and whistles.yml
docassemble/ALToolbox/data/questions/Profiling.yml
docassemble/ALToolbox/data/questions/Shorten a url.yml
docassemble/ALToolbox/data/questions/TextCounter.yml
docassemble/ALToolbox/data/questions/ThreePartsDate.yml
docassemble/ALToolbox/data/questions/addenda_for_docx_text_overflow.yml
docassemble/ALToolbox/data/questions/addenda_for_pdf_text_overflow.yml
docassemble/ALToolbox/data/questions/addenda_for_table_ records_overflow.yml
docassemble/ALToolbox/data/questions/al_income.yml
docassemble/ALToolbox/data/questions/al_income_demo.yml
docassemble/ALToolbox/data/questions/altoolbox_overview.yml
docassemble/ALToolbox/data/questions/business_days_demo.yml
docassemble/ALToolbox/data/questions/chat_completion_demo.yml
docassemble/ALToolbox/data/questions/collapse_template.yml
docassemble/ALToolbox/data/questions/collapse_template_demo.yml
docassemble/ALToolbox/data/questions/copy_button.yml
docassemble/ALToolbox/data/questions/copy_button_demo.yml
docassemble/ALToolbox/data/questions/display_template.yml
docassemble/ALToolbox/data/questions/display_template_demo.yml
docassemble/ALToolbox/data/questions/escape_button.yml
docassemble/ALToolbox/data/questions/escape_button_demo.yml
docassemble_altoolbox-0.13.0.dist-info/licenses/LICENSE
docassemble_altoolbox-0.13.0.dist-info/METADATA
docassemble_altoolbox-0.13.0.dist-info/WHEEL
docassemble_altoolbox-0.13.0.dist-info/top_level.txt
docassemble_altoolbox-0.13.0.dist-info/RECORD
