Metadata-Version: 2.4
Name: docassemble.ALToolbox
Version: 0.13.0
Summary: Collection of small utility functions, classes, and web components for Docassemble interviews
Home-page: https://suffolklitlab.org/docassemble-AssemblyLine-documentation/docs/framework/altoolbox
Author: AssemblyLine
Author-email: 52798256+plocket@users.noreply.github.com
License: The MIT License (MIT)
License-File: LICENSE
Requires-Dist: holidays>=0.38
Requires-Dist: pandas>=2.0.3
Requires-Dist: tiktoken>=0.8.0
Requires-Dist: openai>=1.99.1
Dynamic: author
Dynamic: author-email
Dynamic: description
Dynamic: description-content-type
Dynamic: home-page
Dynamic: license
Dynamic: license-file
Dynamic: requires-dist
Dynamic: summary
